llama_stack_provider_trustyai_fms/__init__.py
llama_stack_provider_trustyai_fms/config.py
llama_stack_provider_trustyai_fms/provider.py
llama_stack_provider_trustyai_fms/detectors/base.py
llama_stack_provider_trustyai_fms/detectors/chat.py
llama_stack_provider_trustyai_fms/detectors/content.py
llama_stack_provider_trustyai_fms-0.2.3.dist-info/licenses/LICENSE.txt
llama_stack_provider_trustyai_fms-0.2.3.dist-info/METADATA
llama_stack_provider_trustyai_fms-0.2.3.dist-info/WHEEL
llama_stack_provider_trustyai_fms-0.2.3.dist-info/entry_points.txt
llama_stack_provider_trustyai_fms-0.2.3.dist-info/top_level.txt
llama_stack_provider_trustyai_fms-0.2.3.dist-info/RECORD
