Metadata-Version: 2.4
Name: llama-stack-provider-trustyai-fms
Version: 0.2.3
Summary: Remote safety provider for Llama Stack integrating FMS Guardrails Orchestrator and community detectors
Author: GitHub: m-misiura
Maintainer: GitHub: m-misiura
License-Expression: Apache-2.0
Project-URL: Homepage, https://github.com/trustyai-explainability/llama-stack-provider-trustyai-fms
Project-URL: Maintainer GitHub, https://github.com/m-misiura
Requires-Python: >=3.12
License-File: LICENSE.txt
Requires-Dist: fastapi
Requires-Dist: opentelemetry-api
Requires-Dist: opentelemetry-exporter-otlp
Requires-Dist: aiosqlite
Requires-Dist: uvicorn
Requires-Dist: ipykernel
Requires-Dist: httpx
Provides-Extra: dev
Requires-Dist: pre-commit; extra == "dev"
Requires-Dist: ruff; extra == "dev"
Provides-Extra: test
Requires-Dist: pytest>=7.0.0; extra == "test"
Requires-Dist: pytest-asyncio>=0.21.0; extra == "test"
Requires-Dist: pytest-httpx>=0.21.0; extra == "test"
Requires-Dist: pytest-mock>=3.10.0; extra == "test"
Requires-Dist: llama-stack==0.2.22; extra == "test"
Dynamic: license-file
